torchvideo/__init__.py
torchvideo-0.0.0.dist-info/METADATA
torchvideo-0.0.0.dist-info/WHEEL
torchvideo-0.0.0.dist-info/top_level.txt
torchvideo-0.0.0.dist-info/RECORD
