Metadata-Version: 2.1
Name: torchvideo
Version: 0.0.0
Summary: PyTorch video dataset library
Home-page: https://github.com/willprice/torchvideo
Author: Will Price
Author-email: will.price94+torchvideo@gmail.com
License: MIT
Platform: UNKNOWN
Classifier: License :: OSI Approved :: MIT License
Classifier: Programming Language :: Python
Classifier: Programming Language :: Python :: 3
Classifier: Programming Language :: Python :: 3.5
Classifier: Programming Language :: Python :: 3.6
Classifier: Programming Language :: Python :: 3.7
Classifier: Programming Language :: Python :: Implementation :: CPython
Classifier: Programming Language :: Python :: Implementation :: PyPy
Requires-Python: >=3.5.0
